mypackage/__init__.py
mypackage/__main__.py
mypackage/mymodule.py
mypackage/mysubpackage/__init__.py
mypackage/mysubpackage/mymoduleinsubpackage.py
mypackage_duce_test-0.1.0.dist-info/METADATA
mypackage_duce_test-0.1.0.dist-info/WHEEL
mypackage_duce_test-0.1.0.dist-info/top_level.txt
mypackage_duce_test-0.1.0.dist-info/RECORD
