Metadata-Version: 2.1
Name: mypackage-duce-test
Version: 0.1.0
Summary: This is test Package
Author: Laurent Wambura
